{"d":"2020-06-30T14:10:53Z","t":"She sat there, chained to her bed, crying. \n\nShe had told her parents that\nshe was homosexual.\n\nAnd now they're going\nto prove her wrong.","c":"Rape wasn't even the worst thing that happened.\nOr maybe it was, I'm no one to judge.\n\n\n\n#chain #bed #cry #homosexuality #wrong #disbelief #parents\n\n\n\n\n\nA little tribute on the last day of #pridemonth.\nhttps://www.marieclaire.co.uk/news/corrective-rape-6626\nhttps://www.wikipedia.org/wiki/Corrective_rape","f":"i","l":["hor","dia"],"h":"https://www.yourquote.in/sherlock-doyle-9qp8/quotes/she-sat-there-chained-bed-crying-she-had-told-parents-she-re-bgwtj1","p":"bgsi4k","n":"bgzvc6"}