{"d":"2020-07-05T15:59:09Z","t":"“Do not go outside,”\nthe emergency broadcast said.\n\n\n\n“Do not listen to their cries for help, no matter how human they sound,” it also said.","c":"I mean, the minorities are never considered human.\n\n\n\n#outside #emergency #broadcast #warning #inhuman #impersonation #lock #capture\n\n\n\n\n\nIf only we had listened and not gone outside, we would have flattened the curve already.\n\nThere's a lot of inspiration for this one, including lockdown, minorities and 'moonstruck'.","f":"i","l":["hor","lif"],"h":"https://www.yourquote.in/sherlock-doyle-9qp8/quotes/do-not-go-outside-emergency-broadcast-said-do-not-listen-no-bhjvi0","p":"bheabm","n":"bho6vh"}