{"d":"2020-12-10T11:25:55Z","t":"Hearing our baby cry, me and my wife started arguing sleepily about whose turn it was to feed the baby.\n\n\n\nWe realized our mistake when an unknown voice whispered, “Don't worry, I'll take care.”\n","c":"Then remembering that the baby was with us in our room, we froze as we heard the sound of footsteps nearing.\n\n\n\n#wife #husband #argument #baby #crying #intruder #unknown #help","f":"i","l":["hor","lif"],"h":"https://www.yourquote.in/sherlock-doyle-9qp8/quotes/hearing-our-baby-cry-me-my-wife-started-arguing-sleepily-it-bv78un","p":"bv53gv","n":"bwczsh"}