{"d":"2020-12-02T09:27:00Z","t":"“Dad, we were playing Hansel and Gretel and Olivia was playing the witch's role.”\n\n\n\nThat's what my kids said when I came into the kitchen and found a pungent smell coming\nfrom the oven.\n","c":"When the screaming stopped, I warned them against killing the kidnapped kids so soon. It's difficult for me to get a new playmate for them everytime.\n\n\n\n#hanselandgretel #fairytale #witch #burn #kill #play #kids #mistake","f":"i","l":["hor","lif"],"h":"https://www.yourquote.in/sherlock-doyle-9qp8/quotes/dad-playing-hansel-gretel-olivia-playing-witch-s-role-s-what-bvo9wd","p":"bvm6gu","n":"bvufnk"}