{"d":"2019-04-14T09:29:51Z","t":"                                          . It looks\n                                              beautiful.\n\nThat's what I thought,\nuntil it blinked.\n\n\n\n\n","c":"Look at the moon tonight. #Collab and share what it makes you feel. #moontonight #YourQuoteAndMine\nCollaborating with YourQuote Baba","f":"i","m":[[118,132]],"l":["hor","lif"],"h":"https://www.yourquote.in/sherlock-doyle-9qp8/quotes/it-looks-beautiful-s-what-i-thought-until-it-blinked-owb8f","p":"otovg","n":"oyw5x"}