{"d":"2019-05-26T06:12:19Z","t":"It has been years since the plague wiped out all life on Earth. Being immune to it, I was the only person alive.\nDesperate of my loneliness, I decided to end my life.\n\nAs I jumped off the building, my phone started ringing.\n\n","c":"Did you get a call?\n\n\n\n\n\n#plague #dystopia #postapocalyptic #earth #sad #suicide #desperation #surprise   ","f":"i","l":["hor","lif"],"h":"https://www.yourquote.in/sherlock-doyle-9qp8/quotes/it-been-years-since-plague-wiped-out-all-life-earth-being-it-qp2gw","p":"qofrp","n":"qp9mj"}